Workbook

Sheet Ventas
A1: DATE | B1: CUSTOMER ID | C1: PRODUCT | D1: LOCATION | E1: ACCOUNT INCOME | F1: SALES COMMISSION | G1: SUBTOTAL | H1: INCOME TAX (ISR) | I1: VAT (IVA) | J1: SHIPPING | K1: TOTAL PROFIT | L1: Year | M1: Quarter
A2: 45451 | B2: Customer 1 | C2: MARTIAN PIN | D2: Baja California | E2: 86.33 | F2: 37.95 | G2: 74.42 | H2: 0.74 | I2: 5.95 | J2: 0 | K2: 41.68 | L2: =YEAR(A2) -> 2024 | M2: =ROUNDUP(MONTH(A2)/3,0) -> 2
A3: 45453 | B3: Customer 2 | C3: HQ3 STABILIZER | D3: Quintana Roo | E3: 1299 | F3: 188.36 | G3: 1119.83 | H3: 11.2 | I3: 89.59 | J3: 95 | K3: 914.86 | L3: =YEAR(A3) -> 2024 | M3: =ROUNDUP(MONTH(A3)/3,0) -> 2
A4: 45457 | B4: Customer 3 | C4: RED GUITAR PIN | D4: Tamaulipas | E4: 86.33 | F4: 37.95 | G4: 74.42 | H4: 0.74 | I4: 5.95 | J4: 0 | K4: 41.68 | L4: =YEAR(A4) -> 2024 | M4: =ROUNDUP(MONTH(A4)/3,0) -> 2
A5: 45459 | B5: Customer 4 | C5: HQ3 STABILIZER | D5: Michoacán | E5: 1299 | F5: 188.36 | G5: 1119.83 | H5: 11.2 | I5: 89.59 | J5: 95 | K5: 914.86 | L5: =YEAR(A5) -> 2024 | M5: =ROUNDUP(MONTH(A5)/3,0) -> 2
A6: 45461 | B6: Customer 5 | C6: AOCHUAN Smart XE STABILIZER | D6: Baja California | E6: 1467 | F6: 212.72 | G6: 1264.66 | H6: 12.65 | I6: 101.17 | J6: 83.4 | K6: 1057.07 | L6: =YEAR(A6) -> 2024 | M6: =ROUNDUP(MONTH(A6)/3,0) -> 2
A7: 45463 | B7: Customer 6 | C7: AOCHUAN Smart XE STABILIZER | D7: Guanajuato | E7: 1699 | F7: 246.36 | G7: 1464.66 | H7: 14.65 | I7: 117.17 | J7: 69.5 | K7: 1251.33 | L7: =YEAR(A7) -> 2024 | M7: =ROUNDUP(MONTH(A7)/3,0) -> 2
A8: 45467 | B8: Customer 7 | C8: AOCHUAN Smart XE STABILIZER | D8: Nuevo León | E8: 1899 | F8: 284.85 | G8: 1637.07 | H8: 16.37 | I8: 130.97 | J8: 69.5 | K8: 1397.31 | L8: =YEAR(A8) -> 2024 | M8: =ROUNDUP(MONTH(A8)/3,0) -> 2
A9: 45467 | B9: Customer 8 | C9: RORETA 3C STABILIZER | D9: State of Mexico | E9: 300 | F9: 0 | G9: 0 | H9: 0 | I9: 0 | J9: 0 | K9: 300 | L9: =YEAR(A9) -> 2024 | M9: =ROUNDUP(MONTH(A9)/3,0) -> 2
A10: 45467 | B10: Customer 8 | C10: RORETA 3C STABILIZER | D10: State of Mexico | E10: 300 | F10: 0 | G10: 0 | H10: 0 | I10: 0 | J10: 0 | K10: 300 | L10: =YEAR(A10) -> 2024 | M10: =ROUNDUP(MONTH(A10)/3,0) -> 2
A11: 45470 | B11: Customer 9 | C11: HQ3 STABILIZER | D11: Coahuila | E11: 1199 | F11: 173.86 | G11: 1033.62 | H11: 10.34 | I11: 82.69 | J11: 95 | K11: 837.12 | L11: =YEAR(A11) -> 2024 | M11: =ROUNDUP(MONTH(A11)/3,0) -> 2
A12: 45472 | B12: Customer 10 | C12: AOCHUAN Smart XE STABILIZER | D12: Sonora | E12: 1699 | F12: 246.36 | G12: 1464.66 | H12: 14.65 | I12: 117.17 | J12: 69.5 | K12: 1251.33 | L12: =YEAR(A12) -> 2024 | M12: =ROUNDUP(MONTH(A12)/3,0) -> 2
A13: 45473 | B13: Customer 11 | C13: 18/PIECE STAINLESS STEEL MANICURE & PEDICURE KIT | D13: State of Mexico | E13: 200 | F13: 0 | G13: 0 | H13: 0 | I13: 0 | J13: 0 | K13: 200 | L13: =YEAR(A13) -> 2024 | M13: =ROUNDUP(MONTH(A13)/3,0) -> 2
... A950: 46225 | B950: Customer 420 | C950: BLACK FRONT SNORKEL | D950: Veracruz | E950: 351.2 | F950: 68.48 | G950: 302.76 | H950: 7.57 | I950: 24.22 | J950: 67.6 | K950: 183.33 | L950: =YEAR(A950) -> 2026 | M950: =ROUNDUP(MONTH(A950)/3,0) -> 3

Sheet Análisis
A1: KPIs PRINCIPALES
A3: Ingreso total | B3: =SUM(Ventas!$E$2:$E$950) -> 857992.67
A4: Utilidad total | B4: =SUM(Ventas!$K$2:$K$950) -> 605336.55
A5: Numero de ventas | B5: =COUNTA(Ventas!$B$2:$B$950) -> 949
A6: Ticket promedio | B6: =B3/B5 -> 904.10187
A7: Utilidad prom. por venta | B7: =B4/B5 -> 637.86781
A8: Margen de utilidad | B8: =B4/B3 -> 0.70552648
A10: UTILIDAD POR AÑO
A11: Año | B11: Utilidad | C11: Crecimiento vs. año anterior
A12: 2024 | B12: =SUMIFS(Ventas!$K$2:$K$950,Ventas!$L$2:$L$950,2024) -> 176150.18 | C12: -
A13: 2025 | B13: =SUMIFS(Ventas!$K$2:$K$950,Ventas!$L$2:$L$950,2025) -> 303622.41 | C13: =(B13-B12)/B12 -> 0.72365654
A14: 2026 | B14: =SUMIFS(Ventas!$K$2:$K$950,Ventas!$L$2:$L$950,2026) -> 125563.96 | C14: =(B14-B13)/B13 -> -0.586447
A15: Nota: 2026 con datos parciales (hasta la ultima fecha registrada).
A17: UTILIDAD POR TRIMESTRE
A18: Trimestre | B18: Utilidad
A19: 24-T2 | B19: =SUMIFS(Ventas!$K$2:$K$950,Ventas!$L$2:$L$950,2024,Ventas!$M$2:$M$950,2) -> 9853.42
A20: 24-T3 | B20: =SUMIFS(Ventas!$K$2:$K$950,Ventas!$L$2:$L$950,2024,Ventas!$M$2:$M$950,3) -> 89487.42
A21: 24-T4 | B21: =SUMIFS(Ventas!$K$2:$K$950,Ventas!$L$2:$L$950,2024,Ventas!$M$2:$M$950,4) -> 76809.34
A22: 25-T1 | B22: =SUMIFS(Ventas!$K$2:$K$950,Ventas!$L$2:$L$950,2025,Ventas!$M$2:$M$950,1) -> 85683.61
A23: 25-T2 | B23: =SUMIFS(Ventas!$K$2:$K$950,Ventas!$L$2:$L$950,2025,Ventas!$M$2:$M$950,2) -> 66926.95
A24: 25-T3 | B24: =SUMIFS(Ventas!$K$2:$K$950,Ventas!$L$2:$L$950,2025,Ventas!$M$2:$M$950,3) -> 79489.08
A25: 25-T4 | B25: =SUMIFS(Ventas!$K$2:$K$950,Ventas!$L$2:$L$950,2025,Ventas!$M$2:$M$950,4) -> 71522.77
A26: 26-T1 | B26: =SUMIFS(Ventas!$K$2:$K$950,Ventas!$L$2:$L$950,2026,Ventas!$M$2:$M$950,1) -> 71102.7
A27: 26-T2 | B27: =SUMIFS(Ventas!$K$2:$K$950,Ventas!$L$2:$L$950,2026,Ventas!$M$2:$M$950,2) -> 47026.69
A28: 26-T3 | B28: =SUMIFS(Ventas!$K$2:$K$950,Ventas!$L$2:$L$950,2026,Ventas!$M$2:$M$950,3) -> 7434.57
A30: UTILIDAD POR PRODUCTO (ordenado de mayor a menor)
A31: Producto | B31: Utilidad | C31: % del total
A32: AOCHUAN Smart XE STABILIZER | B32: =SUMIFS(Ventas!$K$2:$K$950,Ventas!$C$2:$C$950,"AOCHUAN Smart XE STABILIZER") -> 247015.94 | C32: =B32/$B$4 -> 0.40806381
A33: AOCHUAN Smart XE STABILIZER WITH LIGHT | B33: =SUMIFS(Ventas!$K$2:$K$950,Ventas!$C$2:$C$950,"AOCHUAN Smart XE STABILIZER WITH LIGHT") -> 95768.92 | C33: =B33/$B$4 -> 0.15820773
A34: AOCHUAN X PRO STABILIZER (GRAY) | B34: =SUMIFS(Ventas!$K$2:$K$950,Ventas!$C$2:$C$950,"AOCHUAN X PRO STABILIZER (GRAY)") -> 62622.21 | C34: =B34/$B$4 -> 0.10345024
A35: AOCHUAN X PRO STABILIZER (BLACK) | B35: =SUMIFS(Ventas!$K$2:$K$950,Ventas!$C$2:$C$950,"AOCHUAN X PRO STABILIZER (BLACK)") -> 50756.98 | C35: =B35/$B$4 -> 0.083849191
A36: AOCHUAN FILL LIGHT | B36: =SUMIFS(Ventas!$K$2:$K$950,Ventas!$C$2:$C$950,"AOCHUAN FILL LIGHT") -> 20298.49 | C36: =B36/$B$4 -> 0.03353257
A37: BLACK FRONT SNORKEL | B37: =SUMIFS(Ventas!$K$2:$K$950,Ventas!$C$2:$C$950,"BLACK FRONT SNORKEL") -> 10380.84 | C37: =B37/$B$4 -> 0.017148874
A38: S5B STABILIZER | B38: =SUMIFS(Ventas!$K$2:$K$950,Ventas!$C$2:$C$950,"S5B STABILIZER") -> 9903.82 | C38: =B38/$B$4 -> 0.016360849
A39: BLUE FRONT SNORKEL | B39: =SUMIFS(Ventas!$K$2:$K$950,Ventas!$C$2:$C$950,"BLUE FRONT SNORKEL") -> 9598.31 | C39: =B39/$B$4 -> 0.015856155
A40: L7Cpro Plus + AI STABILIZER | B40: =SUMIFS(Ventas!$K$2:$K$950,Ventas!$C$2:$C$950,"L7Cpro Plus + AI STABILIZER") -> 8879.73 | C40: =B40/$B$4 -> 0.01466908
A41: AQUA GREEN FRONT SNORKEL | B41: =SUMIFS(Ventas!$K$2:$K$950,Ventas!$C$2:$C$950,"AQUA GREEN FRONT SNORKEL") -> 7719.29 | C41: =B41/$B$4 -> 0.012752063
A42: S5B PRO STABILIZER | B42: =SUMIFS(Ventas!$K$2:$K$950,Ventas!$C$2:$C$950,"S5B PRO STABILIZER") -> 6842.07 | C42: =B42/$B$4 -> 0.011302919
A43: AOCHUAN X PRO STABILIZER (GRAY) WITH LIGHT | B43: =SUMIFS(Ventas!$K$2:$K$950,Ventas!$C$2:$C$950,"AOCHUAN X PRO STABILIZER (GRAY) WITH LIGHT") -> 6762.86 | C43: =B43/$B$4 -> 0.011172066
A44: HQ3 STABILIZER | B44: =SUMIFS(Ventas!$K$2:$K$950,Ventas!$C$2:$C$950,"HQ3 STABILIZER") -> 6159.09 | C44: =B44/$B$4 -> 0.010174654
A45: PINK FRONT SNORKEL | B45: =SUMIFS(Ventas!$K$2:$K$950,Ventas!$C$2:$C$950,"PINK FRONT SNORKEL") -> 4325.68 | C45: =B45/$B$4 -> 0.0071459092
A46: S5B Pro + AI STABILIZER | B46: =SUMIFS(Ventas!$K$2:$K$950,Ventas!$C$2:$C$950,"S5B Pro + AI STABILIZER") -> 4076.69 | C46: =B46/$B$4 -> 0.0067345843
A47: 3D PUZZLE / SHIP MODEL | B47: =SUMIFS(Ventas!$K$2:$K$950,Ventas!$C$2:$C$950,"3D PUZZLE / SHIP MODEL") -> 3893.54 | C47: =B47/$B$4 -> 0.0064320253
A48: YELLOW FRONT SNORKEL | B48: =SUMIFS(Ventas!$K$2:$K$950,Ventas!$C$2:$C$950,"YELLOW FRONT SNORKEL") -> 3579.27 | C48: =B48/$B$4 -> 0.0059128595
A49: L7Cpro STABILIZER | B49: =SUMIFS(Ventas!$K$2:$K$950,Ventas!$C$2:$C$950,"L7Cpro STABILIZER") -> 3255.63 | C49: =B49/$B$4 -> 0.0053782148
A50: WHITE FRONT SNORKEL | B50: =SUMIFS(Ventas!$K$2:$K$950,Ventas!$C$2:$C$950,"WHITE FRONT SNORKEL") -> 2845.15 | C50: =B50/$B$4 -> 0.0047001127
A51: BLACK MINI CASE FOR GIMBAL STABILIZER | B51: =SUMIFS(Ventas!$K$2:$K$950,Ventas!$C$2:$C$950,"BLACK MINI CASE FOR GIMBAL STABILIZER") -> 2531.41 | C51: =B51/$B$4 -> 0.0041818225
A52: 20/PIECE STAINLESS STEEL MANICURE & PEDICURE KIT | B52: =SUMIFS(Ventas!$K$2:$K$950,Ventas!$C$2:$C$950,"20/PIECE STAINLESS STEEL MANICURE & PEDICURE KIT") -> 2300 | C52: =B52/$B$4 -> 0.0037995393
A53: 3D PUZZLE / CAR MODEL | B53: =SUMIFS(Ventas!$K$2:$K$950,Ventas!$C$2:$C$950,"3D PUZZLE / CAR MODEL") -> 2206.22 | C53: =B53/$B$4 -> 0.0036446172
A54: RED SCALE BICYCLE | B54: =SUMIFS(Ventas!$K$2:$K$950,Ventas!$C$2:$C$950,"RED SCALE BICYCLE") -> 1985.46 | C54: =B54/$B$4 -> 0.0032799275
A55: FINS | B55: =SUMIFS(Ventas!$K$2:$K$950,Ventas!$C$2:$C$950,"FINS") -> 1930.07 | C55: =B55/$B$4 -> 0.0031884247
A56: FG146 75CM | B56: =SUMIFS(Ventas!$K$2:$K$950,Ventas!$C$2:$C$950,"FG146 75CM") -> 1918.71 | C56: =B56/$B$4 -> 0.0031696583
A57: FG167 120CM | B57: =SUMIFS(Ventas!$K$2:$K$950,Ventas!$C$2:$C$950,"FG167 120CM") -> 1733.51 | C57: =B57/$B$4 -> 0.0028637128
A58: GRAY MINI CASE FOR GIMBAL STABILIZER | B58: =SUMIFS(Ventas!$K$2:$K$950,Ventas!$C$2:$C$950,"GRAY MINI CASE FOR GIMBAL STABILIZER") -> 1571.31 | C58: =B58/$B$4 -> 0.0025957626
A59: L9 STABILIZER | B59: =SUMIFS(Ventas!$K$2:$K$950,Ventas!$C$2:$C$950,"L9 STABILIZER") -> 1500 | C59: =B59/$B$4 -> 0.0024779604
A60: HQ6 STABILIZER | B60: =SUMIFS(Ventas!$K$2:$K$950,Ventas!$C$2:$C$950,"HQ6 STABILIZER") -> 1445.22 | C60: =B60/$B$4 -> 0.0023874653
A61: FG146 90CM | B61: =SUMIFS(Ventas!$K$2:$K$950,Ventas!$C$2:$C$950,"FG146 90CM") -> 1370.62 | C61: =B61/$B$4 -> 0.0022642281
A62: 3D PUZZLE / AIRPLANE MODEL | B62: =SUMIFS(Ventas!$K$2:$K$950,Ventas!$C$2:$C$950,"3D PUZZLE / AIRPLANE MODEL") -> 1336.76 | C62: =B62/$B$4 -> 0.0022082922
A63: FG146 60CM | B63: =SUMIFS(Ventas!$K$2:$K$950,Ventas!$C$2:$C$950,"FG146 60CM") -> 1308.2 | C63: =B63/$B$4 -> 0.0021611119
A64: 18/PIECE STAINLESS STEEL MANICURE & PEDICURE KIT | B64: =SUMIFS(Ventas!$K$2:$K$950,Ventas!$C$2:$C$950,"18/PIECE STAINLESS STEEL MANICURE & PEDICURE KIT") -> 1260 | C64: =B64/$B$4 -> 0.0020814867
A65: BLUE SCALE BICYCLE | B65: =SUMIFS(Ventas!$K$2:$K$950,Ventas!$C$2:$C$950,"BLUE SCALE BICYCLE") -> 1116.17 | C65: =B65/$B$4 -> 0.0018438834
A66: FG167 30CM | B66: =SUMIFS(Ventas!$K$2:$K$950,Ventas!$C$2:$C$950,"FG167 30CM") -> 940.04 | C66: =B66/$B$4 -> 0.0015529213
A67: FG146 120CM | B67: =SUMIFS(Ventas!$K$2:$K$950,Ventas!$C$2:$C$950,"FG146 120CM") -> 936.94 | C67: =B67/$B$4 -> 0.0015478001
A68: FLUORESCENT YELLOW & BLACK SCALE BICYCLE | B68: =SUMIFS(Ventas!$K$2:$K$950,Ventas!$C$2:$C$950,"FLUORESCENT YELLOW & BLACK SCALE BICYCLE") -> 849.76 | C68: =B68/$B$4 -> 0.0014037811
A69: MINI BAG FOR AOCHUAN STABILIZER | B69: =SUMIFS(Ventas!$K$2:$K$950,Ventas!$C$2:$C$950,"MINI BAG FOR AOCHUAN STABILIZER") -> 843.2 | C69: =B69/$B$4 -> 0.0013929441
A70: DIGITAL BLOOD PRESSURE MONITOR | B70: =SUMIFS(Ventas!$K$2:$K$950,Ventas!$C$2:$C$950,"DIGITAL BLOOD PRESSURE MONITOR") -> 800 | C70: =B70/$B$4 -> 0.0013215789
A71: FG138 75CM | B71: =SUMIFS(Ventas!$K$2:$K$950,Ventas!$C$2:$C$950,"FG138 75CM") -> 777.35 | C71: =B71/$B$4 -> 0.0012841617
A72: FG167 45CM | B72: =SUMIFS(Ventas!$K$2:$K$950,Ventas!$C$2:$C$950,"FG167 45CM") -> 775.03 | C72: =B72/$B$4 -> 0.0012803291
A73: FG146 45CM | B73: =SUMIFS(Ventas!$K$2:$K$950,Ventas!$C$2:$C$950,"FG146 45CM") -> 656.74 | C73: =B73/$B$4 -> 0.0010849171
A74: YELLOW SCALE BICYCLE | B74: =SUMIFS(Ventas!$K$2:$K$950,Ventas!$C$2:$C$950,"YELLOW SCALE BICYCLE") -> 635.96 | C74: =B74/$B$4 -> 0.0010505891
A75: RORETA 3C STABILIZER | B75: =SUMIFS(Ventas!$K$2:$K$950,Ventas!$C$2:$C$950,"RORETA 3C STABILIZER") -> 600 | C75: =B75/$B$4 -> 0.00099118416
A76: F8 STABILIZER | B76: =SUMIFS(Ventas!$K$2:$K$950,Ventas!$C$2:$C$950,"F8 STABILIZER") -> 600 | C76: =B76/$B$4 -> 0.00099118416
A77: FG167 60CM | B77: =SUMIFS(Ventas!$K$2:$K$950,Ventas!$C$2:$C$950,"FG167 60CM") -> 600 | C77: =B77/$B$4 -> 0.00099118416
A78: F10 STABILIZER | B78: =SUMIFS(Ventas!$K$2:$K$950,Ventas!$C$2:$C$950,"F10 STABILIZER") -> 600 | C78: =B78/$B$4 -> 0.00099118416
A79: 3D PUZZLE / TRAIN MODEL | B79: =SUMIFS(Ventas!$K$2:$K$950,Ventas!$C$2:$C$950,"3D PUZZLE / TRAIN MODEL") -> 585.88 | C79: =B79/$B$4 -> 0.00096785829
A80: BLUE GIMBAL STABILIZER CASE | B80: =SUMIFS(Ventas!$K$2:$K$950,Ventas!$C$2:$C$950,"BLUE GIMBAL STABILIZER CASE") -> 498.54 | C80: =B80/$B$4 -> 0.00082357492
A81: BLACK SCALE BICYCLE | B81: =SUMIFS(Ventas!$K$2:$K$950,Ventas!$C$2:$C$950,"BLACK SCALE BICYCLE") -> 486.64 | C81: =B81/$B$4 -> 0.00080391643
A82: A10 STABILIZER (BLACK) | B82: =SUMIFS(Ventas!$K$2:$K$950,Ventas!$C$2:$C$950,"A10 STABILIZER (BLACK)") -> 439.37 | C82: =B82/$B$4 -> 0.00072582764
A83: ORANGE SCALE BICYCLE | B83: =SUMIFS(Ventas!$K$2:$K$950,Ventas!$C$2:$C$950,"ORANGE SCALE BICYCLE") -> 321.76 | C83: =B83/$B$4 -> 0.00053153903
A84: FG146 30CM | B84: =SUMIFS(Ventas!$K$2:$K$950,Ventas!$C$2:$C$950,"FG146 30CM") -> 319 | C84: =B84/$B$4 -> 0.00052697958
A85: FG138 90CM | B85: =SUMIFS(Ventas!$K$2:$K$950,Ventas!$C$2:$C$950,"FG138 90CM") -> 300 | C85: =B85/$B$4 -> 0.00049559208
A86: MINI KAWAII LAMP | B86: =SUMIFS(Ventas!$K$2:$K$950,Ventas!$C$2:$C$950,"MINI KAWAII LAMP") -> 300 | C86: =B86/$B$4 -> 0.00049559208
A87: SCALE MOTORCYCLE 1 (WHITE & RED) | B87: =SUMIFS(Ventas!$K$2:$K$950,Ventas!$C$2:$C$950,"SCALE MOTORCYCLE 1 (WHITE & RED)") -> 300 | C87: =B87/$B$4 -> 0.00049559208
A88: GREEN CASSETTE "GOOD VIBES" PIN | B88: =SUMIFS(Ventas!$K$2:$K$950,Ventas!$C$2:$C$950,"GREEN CASSETTE ""GOOD VIBES"" PIN") -> 255.82 | C88: =B88/$B$4 -> 0.00042260789
A89: FG147 CLIP ON 30CM | B89: =SUMIFS(Ventas!$K$2:$K$950,Ventas!$C$2:$C$950,"FG147 CLIP ON 30CM") -> 252.67 | C89: =B89/$B$4 -> 0.00041740417
A90: 12/PIECE STAINLESS STEEL MANICURE & PEDICURE KIT | B90: =SUMIFS(Ventas!$K$2:$K$950,Ventas!$C$2:$C$950,"12/PIECE STAINLESS STEEL MANICURE & PEDICURE KIT") -> 180 | C90: =B90/$B$4 -> 0.00029735525
A91: CATSA PIN | B91: =SUMIFS(Ventas!$K$2:$K$950,Ventas!$C$2:$C$950,"CATSA PIN") -> 164 | C91: =B91/$B$4 -> 0.00027092367
A92: RED GUITAR PIN | B92: =SUMIFS(Ventas!$K$2:$K$950,Ventas!$C$2:$C$950,"RED GUITAR PIN") -> 148.74 | C92: =B92/$B$4 -> 0.00024571455
A93: SCALE MOTORCYCLE 2 (BLACK & YELLOW) | B93: =SUMIFS(Ventas!$K$2:$K$950,Ventas!$C$2:$C$950,"SCALE MOTORCYCLE 2 (BLACK & YELLOW)") -> 148 | C93: =B93/$B$4 -> 0.00024449209
A94: SCALE MOTORCYCLE 5 (BLACK) | B94: =SUMIFS(Ventas!$K$2:$K$950,Ventas!$C$2:$C$950,"SCALE MOTORCYCLE 5 (BLACK)") -> 146.03 | C94: =B94/$B$4 -> 0.0002412377
A95: DISC ON TURNTABLE PIN | B95: =SUMIFS(Ventas!$K$2:$K$950,Ventas!$C$2:$C$950,"DISC ON TURNTABLE PIN") -> 112.48 | C95: =B95/$B$4 -> 0.00018581399
A96: MELTED DISC PIN (DISC 1) | B96: =SUMIFS(Ventas!$K$2:$K$950,Ventas!$C$2:$C$950,"MELTED DISC PIN (DISC 1)") -> 112.48 | C96: =B96/$B$4 -> 0.00018581399
A97: WINE & GLASS PIN | B97: =SUMIFS(Ventas!$K$2:$K$950,Ventas!$C$2:$C$950,"WINE & GLASS PIN") -> 78.38 | C97: =B97/$B$4 -> 0.00012948169
A98: HEART & FLOWER PIN | B98: =SUMIFS(Ventas!$K$2:$K$950,Ventas!$C$2:$C$950,"HEART & FLOWER PIN") -> 73.65 | C98: =B98/$B$4 -> 0.00012166786
A99: BLACK CASSETTE "SAD SONG" PIN | B99: =SUMIFS(Ventas!$K$2:$K$950,Ventas!$C$2:$C$950,"BLACK CASSETTE ""SAD SONG"" PIN") -> 67 | C99: =B99/$B$4 -> 0.00011068223
A100: "THAT'S WHAT SHE SAID" PIN | B100: =SUMIFS(Ventas!$K$2:$K$950,Ventas!$C$2:$C$950,"""THAT'S WHAT SHE SAID"" PIN") -> 51.01 | C100: =B100/$B$4 -> 8.4267173e-05
A101: MARTIAN PIN | B101: =SUMIFS(Ventas!$K$2:$K$950,Ventas!$C$2:$C$950,"MARTIAN PIN") -> 41.68 | C101: =B101/$B$4 -> 6.885426e-05
A102: PINK CASSETTE "BEST 90'S" PIN | B102: =SUMIFS(Ventas!$K$2:$K$950,Ventas!$C$2:$C$950,"PINK CASSETTE ""BEST 90'S"" PIN") -> 39.73 | C102: =B102/$B$4 -> 6.5632911e-05
A103: FEMINIST FIST PIN | B103: =SUMIFS(Ventas!$K$2:$K$950,Ventas!$C$2:$C$950,"FEMINIST FIST PIN") -> 36.73 | C103: =B103/$B$4 -> 6.067699e-05
A104: "I BELIEVE" PIN | B104: =SUMIFS(Ventas!$K$2:$K$950,Ventas!$C$2:$C$950,"""I BELIEVE"" PIN") -> 33.5 | C104: =B104/$B$4 -> 5.5341116e-05
...

Sheet Dashboard
B2: DASHBOARD DE VENTAS
B4: INGRESO TOTAL | D4: UTILIDAD TOTAL | F4: NUMERO DE VENTAS | H4: TICKET PROMEDIO | J4: MARGEN DE UTILIDAD
B5: =Análisis!B3 -> 857992.67 | D5: =Análisis!B4 -> 605336.55 | F5: =Análisis!B5 -> 949 | H5: =Análisis!B6 -> 904.10187 | J5: =Análisis!B8 -> 0.70552648
